cosmian_secure_computation_client/__init__.py
cosmian_secure_computation_client/computations.py
cosmian_secure_computation_client/log.py
cosmian_secure_computation_client/side.py
cosmian_secure_computation_client/api/__init__.py
cosmian_secure_computation_client/api/auth.py
cosmian_secure_computation_client/api/provider.py
cosmian_secure_computation_client/api/remote_attestation.py
cosmian_secure_computation_client/crypto/__init__.py
cosmian_secure_computation_client/crypto/context.py
cosmian_secure_computation_client/crypto/helper.py
cosmian_secure_computation_client/participant/__init__.py
cosmian_secure_computation_client/participant/base.py
cosmian_secure_computation_client/participant/code_provider.py
cosmian_secure_computation_client/participant/computation_owner.py
cosmian_secure_computation_client/participant/data_provider.py
cosmian_secure_computation_client/participant/result_consumer.py
cosmian_secure_computation_client/util/__init__.py
cosmian_secure_computation_client/util/base64.py
cosmian_secure_computation_client/util/entrypoint.py
cosmian_secure_computation_client/util/fs.py
cosmian_secure_computation_client/util/mnemonic.py
cosmian_secure_computation_client-0.5.0.dist-info/METADATA
cosmian_secure_computation_client-0.5.0.dist-info/WHEEL
cosmian_secure_computation_client-0.5.0.dist-info/top_level.txt
cosmian_secure_computation_client-0.5.0.dist-info/zip-safe
cosmian_secure_computation_client-0.5.0.dist-info/RECORD
