Metadata-Version: 2.1
Name: cosmian-secure-computation-client
Version: 0.5.0
Summary: Python client library for Cosmian Secure Computation
Home-page: https://cosmian.com
Author: Cosmian Tech
Author-email: tech@cosmian.com
License: MIT
Classifier: Development Status :: 5 - Production/Stable
Classifier: Environment :: Console
Classifier: License :: OSI Approved :: MIT License
Classifier: Programming Language :: Python :: 3.8
Classifier: Programming Language :: Python :: 3.9
Requires-Python: >=3.8.0
Requires-Dist: requests (<3.0.0,>=2.28.1)
Requires-Dist: pynacl (<1.6.0,>=1.5.0)
Requires-Dist: cryptography (<39.0.0,>=38.0.1)
Requires-Dist: pyjwt (<2.6.0,>=2.5.0)
Requires-Dist: urllib3 (<1.27.0,>=1.26.12)
